SolubilityModels
