Metadata-Version: 2.1
Name: SolubilityModels
Version: 1.8.0
Summary: Tool for computational analysis of solubility models
Home-page: https://github.com/SolubilityGroup/Thermodynamic_Solutions
Author: Solubility Group
Author-email: solubilitygroup@gmail.com
License: CC BY-NC-SA 4.0
Download-URL: https://github.com/SolubilityGroup/Thermodynamic_Solutions/blob/main/ThermodynamicSolutions/SolubilityModels.py
Keywords: solubility,solubility models,dissolution thermodynamics,apelblat,modified apelblat,vant hoff,yaws,modified wilson,wilson,buchowski ksiazaczak,λh model
Platform: UNKNOWN
Classifier: Development Status :: 4 - Beta
Classifier: Intended Audience :: Developers
Classifier: Topic :: Software Development :: Build Tools
Classifier: Programming Language :: Python :: 3.4
Classifier: Programming Language :: Python :: 3.5
Classifier: Programming Language :: Python :: 3.6
Classifier: Programming Language :: Python :: 3.7
Classifier: Programming Language :: Python :: 3.8
Classifier: Programming Language :: Python :: 3.9
License-File: LICENSE
